mytiktok/__init__.py
mytiktok/account_videos.py
mytiktok/base.py
mytiktok/exceptions.py
mytiktok/helper.py
mytiktok/login.py
mytiktok/tiktok.py
mytiktok/video.py
mytiktok/videos.py
mytiktok/Data/__init__.py
mytiktok/Data/cookie_names.txt
mytiktok/Data/cookies_analysis copy.txt
mytiktok/Data/cookies_analysis.txt
mytiktok-0.0.5.dist-info/LICENSE
mytiktok-0.0.5.dist-info/METADATA
mytiktok-0.0.5.dist-info/WHEEL
mytiktok-0.0.5.dist-info/top_level.txt
mytiktok-0.0.5.dist-info/RECORD
