Metadata-Version: 2.1
Name: mytiktok
Version: 0.0.5
Summary: A Simple Python Package for Scarping and Downloading Tiktok Videos
Author-email: Dragoneyes <yolo89381@gmail.com>
Project-URL: Homepage, https://github.com/geovanigaldemsugar/Mytiktok
Classifier: Programming Language :: Python :: 3
Classifier: License :: OSI Approved :: MIT License
Classifier: Operating System :: OS Independent
License-File: LICENSE
Requires-Dist: backports.tarfile ==1.1.1
Requires-Dist: blinker ==1.8.1
Requires-Dist: Brotli ==1.1.0
Requires-Dist: certifi ==2024.2.2
Requires-Dist: cffi ==1.16.0
Requires-Dist: charset-normalizer ==3.3.2
Requires-Dist: cryptography ==42.0.5
Requires-Dist: docutils ==0.21.2
Requires-Dist: exceptiongroup ==1.2.1
Requires-Dist: fake-useragent ==1.5.1
Requires-Dist: h11 ==0.14.0
Requires-Dist: h2 ==4.1.0
Requires-Dist: hpack ==4.0.0
Requires-Dist: hyperframe ==6.0.1
Requires-Dist: idna ==3.7
Requires-Dist: importlib-metadata ==7.1.0
Requires-Dist: jaraco.classes ==3.4.0
Requires-Dist: jaraco.context ==5.3.0
Requires-Dist: jaraco.functools ==4.0.1
Requires-Dist: jeepney ==0.8.0
Requires-Dist: kaitaistruct ==0.10
Requires-Dist: keyring ==25.2.0
Requires-Dist: markdown-it-py ==3.0.0
Requires-Dist: mdurl ==0.1.2
Requires-Dist: more-itertools ==10.2.0
Requires-Dist: nh3 ==0.2.17
Requires-Dist: outcome ==1.3.0.post0
Requires-Dist: pathvalidate ==3.2.0
Requires-Dist: pkginfo ==1.10.0
Requires-Dist: pyasn1 ==0.6.0
Requires-Dist: pycparser ==2.22
Requires-Dist: Pygments ==2.17.2
Requires-Dist: pyOpenSSL ==24.1.0
Requires-Dist: pyparsing ==3.1.2
Requires-Dist: PySocks ==1.7.1
Requires-Dist: python-dotenv ==1.0.1
Requires-Dist: readme-renderer ==43.0
Requires-Dist: requests ==2.31.0
Requires-Dist: requests-toolbelt ==1.0.0
Requires-Dist: rfc3986 ==2.0.0
Requires-Dist: rich ==13.7.1
Requires-Dist: SecretStorage ==3.3.3
Requires-Dist: selenium ==4.20.0
Requires-Dist: sniffio ==1.3.1
Requires-Dist: sortedcontainers ==2.4.0
Requires-Dist: tenacity ==8.2.3
Requires-Dist: trio ==0.25.0
Requires-Dist: trio-websocket ==0.11.1
Requires-Dist: typing-extensions ==4.11.0
Requires-Dist: undetected-chromedriver ==3.5.5
Requires-Dist: urllib3 ==2.2.1
Requires-Dist: websockets ==12.0
Requires-Dist: wsproto ==1.2.0
Requires-Dist: zipp ==3.18.1
Requires-Dist: zstandard ==0.22.0
